pydme/__init__.py
pydme-0.2.2.dist-info/WHEEL
pydme-0.2.2.dist-info/METADATA
pydme-0.2.2.dist-info/RECORD
