Metadata-Version: 2.1
Name: pydme
Version: 0.2.2
Summary: Hook into the Dolphin emulator and manipulate the memory
Home-page: https://gitlab.com/OpenDisrupt/pydme
Author: Maximillian Strand
Author-email: maximillian.strand@protonmail.com
Requires-Python: >=3.9,<4.0
Classifier: Programming Language :: Python :: 3
Classifier: Programming Language :: Python :: 3.10
Classifier: Programming Language :: Python :: 3.9
Requires-Dist: dolphin-memory-engine (>=1.1.0,<2.0.0)
Project-URL: Repository, https://gitlab.com/OpenDisrupt/pydme
